response_formatter/__init__.py
response_formatter/formatter.py
response_decorator_moms-0.0.1.dist-info/METADATA
response_decorator_moms-0.0.1.dist-info/WHEEL
response_decorator_moms-0.0.1.dist-info/top_level.txt
response_decorator_moms-0.0.1.dist-info/RECORD
