Metadata-Version: 2.1
Name: response-decorator-moms
Version: 0.0.1
Summary: Its a response formatter
Home-page: UNKNOWN
Author: Rakesh Khulbe
Author-email: merakeshkhulbe@gmail.com
License: UNKNOWN
Platform: UNKNOWN
Classifier: Programming Language :: Python :: 3
Requires-Python: >=3.6
